[
  {
    "route": "/",
    "viewport": "mobile",
    "screenshot": ".visual-regression/home.mobile.png",
    "flags": [
      {
        "tag": "span",
        "cls": "vk-receipt-stamp",
        "text": "Fast pris",
        "color": "rgb(232, 80, 10)",
        "bg": "rgb(255, 255, 255)",
        "y": 4999,
        "hex": "#e8500a",
        "contrast": 3.76,
        "reasons": [
          "low-contrast(3.76)"
        ]
      },
      {
        "tag": "span",
        "cls": "vk-receipt-stamp",
        "text": "Fast pris",
        "color": "rgb(232, 80, 10)",
        "bg": "rgb(255, 255, 255)",
        "y": 5322,
        "hex": "#e8500a",
        "contrast": 3.76,
        "reasons": [
          "low-contrast(3.76)"
        ]
      },
      {
        "tag": "span",
        "cls": "vk-receipt-stamp",
        "text": "Fast pris",
        "color": "rgb(232, 80, 10)",
        "bg": "rgb(255, 255, 255)",
        "y": 5645,
        "hex": "#e8500a",
        "contrast": 3.76,
        "reasons": [
          "low-contrast(3.76)"
        ]
      }
    ]
  },
  {
    "route": "/priser",
    "viewport": "mobile",
    "screenshot": ".visual-regression/priser.mobile.png",
    "flags": [
      {
        "tag": "span",
        "cls": "vk-receipt-stamp",
        "text": "Fast pris",
        "color": "rgb(232, 80, 10)",
        "bg": "rgb(255, 255, 255)",
        "y": 823,
        "hex": "#e8500a",
        "contrast": 3.76,
        "reasons": [
          "low-contrast(3.76)"
        ]
      },
      {
        "tag": "span",
        "cls": "vk-receipt-stamp",
        "text": "Fast pris",
        "color": "rgb(232, 80, 10)",
        "bg": "rgb(255, 255, 255)",
        "y": 1401,
        "hex": "#e8500a",
        "contrast": 3.76,
        "reasons": [
          "low-contrast(3.76)"
        ]
      },
      {
        "tag": "span",
        "cls": "vk-receipt-stamp",
        "text": "Fast pris",
        "color": "rgb(232, 80, 10)",
        "bg": "rgb(255, 255, 255)",
        "y": 1979,
        "hex": "#e8500a",
        "contrast": 3.76,
        "reasons": [
          "low-contrast(3.76)"
        ]
      },
      {
        "tag": "span",
        "cls": "vk-receipt-stamp",
        "text": "Fast pris",
        "color": "rgb(232, 80, 10)",
        "bg": "rgb(255, 255, 255)",
        "y": 2557,
        "hex": "#e8500a",
        "contrast": 3.76,
        "reasons": [
          "low-contrast(3.76)"
        ]
      }
    ]
  },
  {
    "route": "/tjanster",
    "viewport": "mobile",
    "screenshot": ".visual-regression/tjanster.mobile.png",
    "flags": []
  },
  {
    "route": "/tjanster/webbdesign",
    "viewport": "mobile",
    "screenshot": ".visual-regression/tjanster_webbdesign.mobile.png",
    "flags": []
  },
  {
    "route": "/tjanster/seo",
    "viewport": "mobile",
    "screenshot": ".visual-regression/tjanster_seo.mobile.png",
    "flags": [
      {
        "tag": "span",
        "cls": "",
        "text": "01",
        "color": "rgb(138, 133, 120)",
        "bg": "rgb(246, 245, 241)",
        "y": 736,
        "hex": "#8a8578",
        "contrast": 3.37,
        "reasons": [
          "low-contrast(3.37)"
        ]
      },
      {
        "tag": "span",
        "cls": "",
        "text": "02",
        "color": "rgb(138, 133, 120)",
        "bg": "rgb(246, 245, 241)",
        "y": 794,
        "hex": "#8a8578",
        "contrast": 3.37,
        "reasons": [
          "low-contrast(3.37)"
        ]
      },
      {
        "tag": "span",
        "cls": "",
        "text": "03",
        "color": "rgb(138, 133, 120)",
        "bg": "rgb(246, 245, 241)",
        "y": 829,
        "hex": "#8a8578",
        "contrast": 3.37,
        "reasons": [
          "low-contrast(3.37)"
        ]
      },
      {
        "tag": "span",
        "cls": "",
        "text": "04",
        "color": "rgb(138, 133, 120)",
        "bg": "rgb(246, 245, 241)",
        "y": 864,
        "hex": "#8a8578",
        "contrast": 3.37,
        "reasons": [
          "low-contrast(3.37)"
        ]
      },
      {
        "tag": "span",
        "cls": "",
        "text": "05",
        "color": "rgb(138, 133, 120)",
        "bg": "rgb(246, 245, 241)",
        "y": 922,
        "hex": "#8a8578",
        "contrast": 3.37,
        "reasons": [
          "low-contrast(3.37)"
        ]
      },
      {
        "tag": "span",
        "cls": "",
        "text": "06",
        "color": "rgb(138, 133, 120)",
        "bg": "rgb(246, 245, 241)",
        "y": 980,
        "hex": "#8a8578",
        "contrast": 3.37,
        "reasons": [
          "low-contrast(3.37)"
        ]
      },
      {
        "tag": "span",
        "cls": "",
        "text": "07",
        "color": "rgb(138, 133, 120)",
        "bg": "rgb(246, 245, 241)",
        "y": 1015,
        "hex": "#8a8578",
        "contrast": 3.37,
        "reasons": [
          "low-contrast(3.37)"
        ]
      },
      {
        "tag": "span",
        "cls": "",
        "text": "08",
        "color": "rgb(138, 133, 120)",
        "bg": "rgb(246, 245, 241)",
        "y": 1050,
        "hex": "#8a8578",
        "contrast": 3.37,
        "reasons": [
          "low-contrast(3.37)"
        ]
      },
      {
        "tag": "span",
        "cls": "",
        "text": "01",
        "color": "rgb(138, 133, 120)",
        "bg": "rgb(246, 245, 241)",
        "y": 1231,
        "hex": "#8a8578",
        "contrast": 3.37,
        "reasons": [
          "low-contrast(3.37)"
        ]
      },
      {
        "tag": "span",
        "cls": "",
        "text": "02",
        "color": "rgb(138, 133, 120)",
        "bg": "rgb(246, 245, 241)",
        "y": 1342,
        "hex": "#8a8578",
        "contrast": 3.37,
        "reasons": [
          "low-contrast(3.37)"
        ]
      },
      {
        "tag": "span",
        "cls": "",
        "text": "03",
        "color": "rgb(138, 133, 120)",
        "bg": "rgb(246, 245, 241)",
        "y": 1452,
        "hex": "#8a8578",
        "contrast": 3.37,
        "reasons": [
          "low-contrast(3.37)"
        ]
      },
      {
        "tag": "span",
        "cls": "",
        "text": "04",
        "color": "rgb(138, 133, 120)",
        "bg": "rgb(246, 245, 241)",
        "y": 1562,
        "hex": "#8a8578",
        "contrast": 3.37,
        "reasons": [
          "low-contrast(3.37)"
        ]
      }
    ]
  },
  {
    "route": "/tjanster/ai-automation",
    "viewport": "mobile",
    "screenshot": ".visual-regression/tjanster_ai-automation.mobile.png",
    "flags": []
  },
  {
    "route": "/ai-karta",
    "viewport": "mobile",
    "screenshot": ".visual-regression/ai-karta.mobile.png",
    "flags": []
  },
  {
    "route": "/arbete",
    "viewport": "mobile",
    "screenshot": ".visual-regression/arbete.mobile.png",
    "flags": []
  },
  {
    "route": "/om",
    "viewport": "mobile",
    "screenshot": ".visual-regression/om.mobile.png",
    "flags": []
  },
  {
    "route": "/kontakt",
    "viewport": "mobile",
    "screenshot": ".visual-regression/kontakt.mobile.png",
    "flags": []
  },
  {
    "route": "/integritetspolicy",
    "viewport": "mobile",
    "screenshot": ".visual-regression/integritetspolicy.mobile.png",
    "flags": []
  },
  {
    "route": "/redaktionell-policy",
    "viewport": "mobile",
    "screenshot": ".visual-regression/redaktionell-policy.mobile.png",
    "flags": []
  },
  {
    "route": "/",
    "viewport": "desktop",
    "screenshot": ".visual-regression/home.desktop.png",
    "flags": [
      {
        "tag": "span",
        "cls": "vk-receipt-stamp",
        "text": "Fast pris",
        "color": "rgb(232, 80, 10)",
        "bg": "rgb(255, 255, 255)",
        "y": 3859,
        "hex": "#e8500a",
        "contrast": 3.76,
        "reasons": [
          "low-contrast(3.76)"
        ]
      },
      {
        "tag": "span",
        "cls": "vk-receipt-stamp",
        "text": "Fast pris",
        "color": "rgb(232, 80, 10)",
        "bg": "rgb(255, 255, 255)",
        "y": 3859,
        "hex": "#e8500a",
        "contrast": 3.76,
        "reasons": [
          "low-contrast(3.76)"
        ]
      },
      {
        "tag": "span",
        "cls": "vk-receipt-stamp",
        "text": "Fast pris",
        "color": "rgb(232, 80, 10)",
        "bg": "rgb(255, 255, 255)",
        "y": 3859,
        "hex": "#e8500a",
        "contrast": 3.76,
        "reasons": [
          "low-contrast(3.76)"
        ]
      }
    ]
  },
  {
    "route": "/priser",
    "viewport": "desktop",
    "screenshot": ".visual-regression/priser.desktop.png",
    "flags": [
      {
        "tag": "span",
        "cls": "vk-receipt-stamp",
        "text": "Fast pris",
        "color": "rgb(232, 80, 10)",
        "bg": "rgb(255, 255, 255)",
        "y": 1015,
        "hex": "#e8500a",
        "contrast": 3.76,
        "reasons": [
          "low-contrast(3.76)"
        ]
      },
      {
        "tag": "span",
        "cls": "vk-receipt-stamp",
        "text": "Fast pris",
        "color": "rgb(232, 80, 10)",
        "bg": "rgb(255, 255, 255)",
        "y": 1015,
        "hex": "#e8500a",
        "contrast": 3.76,
        "reasons": [
          "low-contrast(3.76)"
        ]
      },
      {
        "tag": "span",
        "cls": "vk-receipt-stamp",
        "text": "Fast pris",
        "color": "rgb(232, 80, 10)",
        "bg": "rgb(255, 255, 255)",
        "y": 1015,
        "hex": "#e8500a",
        "contrast": 3.76,
        "reasons": [
          "low-contrast(3.76)"
        ]
      },
      {
        "tag": "span",
        "cls": "vk-receipt-stamp",
        "text": "Fast pris",
        "color": "rgb(232, 80, 10)",
        "bg": "rgb(255, 255, 255)",
        "y": 1015,
        "hex": "#e8500a",
        "contrast": 3.76,
        "reasons": [
          "low-contrast(3.76)"
        ]
      }
    ]
  },
  {
    "route": "/tjanster",
    "viewport": "desktop",
    "screenshot": ".visual-regression/tjanster.desktop.png",
    "flags": []
  },
  {
    "route": "/tjanster/webbdesign",
    "viewport": "desktop",
    "screenshot": ".visual-regression/tjanster_webbdesign.desktop.png",
    "flags": []
  },
  {
    "route": "/tjanster/seo",
    "viewport": "desktop",
    "screenshot": ".visual-regression/tjanster_seo.desktop.png",
    "flags": [
      {
        "tag": "span",
        "cls": "",
        "text": "01",
        "color": "rgb(138, 133, 120)",
        "bg": "rgb(246, 245, 241)",
        "y": 901,
        "hex": "#8a8578",
        "contrast": 3.37,
        "reasons": [
          "low-contrast(3.37)"
        ]
      },
      {
        "tag": "span",
        "cls": "",
        "text": "02",
        "color": "rgb(138, 133, 120)",
        "bg": "rgb(246, 245, 241)",
        "y": 938,
        "hex": "#8a8578",
        "contrast": 3.37,
        "reasons": [
          "low-contrast(3.37)"
        ]
      },
      {
        "tag": "span",
        "cls": "",
        "text": "03",
        "color": "rgb(138, 133, 120)",
        "bg": "rgb(246, 245, 241)",
        "y": 976,
        "hex": "#8a8578",
        "contrast": 3.37,
        "reasons": [
          "low-contrast(3.37)"
        ]
      },
      {
        "tag": "span",
        "cls": "",
        "text": "04",
        "color": "rgb(138, 133, 120)",
        "bg": "rgb(246, 245, 241)",
        "y": 1013,
        "hex": "#8a8578",
        "contrast": 3.37,
        "reasons": [
          "low-contrast(3.37)"
        ]
      },
      {
        "tag": "span",
        "cls": "",
        "text": "05",
        "color": "rgb(138, 133, 120)",
        "bg": "rgb(246, 245, 241)",
        "y": 1051,
        "hex": "#8a8578",
        "contrast": 3.37,
        "reasons": [
          "low-contrast(3.37)"
        ]
      },
      {
        "tag": "span",
        "cls": "",
        "text": "06",
        "color": "rgb(138, 133, 120)",
        "bg": "rgb(246, 245, 241)",
        "y": 1089,
        "hex": "#8a8578",
        "contrast": 3.37,
        "reasons": [
          "low-contrast(3.37)"
        ]
      },
      {
        "tag": "span",
        "cls": "",
        "text": "07",
        "color": "rgb(138, 133, 120)",
        "bg": "rgb(246, 245, 241)",
        "y": 1126,
        "hex": "#8a8578",
        "contrast": 3.37,
        "reasons": [
          "low-contrast(3.37)"
        ]
      },
      {
        "tag": "span",
        "cls": "",
        "text": "08",
        "color": "rgb(138, 133, 120)",
        "bg": "rgb(246, 245, 241)",
        "y": 1164,
        "hex": "#8a8578",
        "contrast": 3.37,
        "reasons": [
          "low-contrast(3.37)"
        ]
      },
      {
        "tag": "span",
        "cls": "",
        "text": "01",
        "color": "rgb(138, 133, 120)",
        "bg": "rgb(246, 245, 241)",
        "y": 1411,
        "hex": "#8a8578",
        "contrast": 3.37,
        "reasons": [
          "low-contrast(3.37)"
        ]
      },
      {
        "tag": "span",
        "cls": "",
        "text": "02",
        "color": "rgb(138, 133, 120)",
        "bg": "rgb(246, 245, 241)",
        "y": 1499,
        "hex": "#8a8578",
        "contrast": 3.37,
        "reasons": [
          "low-contrast(3.37)"
        ]
      },
      {
        "tag": "span",
        "cls": "",
        "text": "03",
        "color": "rgb(138, 133, 120)",
        "bg": "rgb(246, 245, 241)",
        "y": 1586,
        "hex": "#8a8578",
        "contrast": 3.37,
        "reasons": [
          "low-contrast(3.37)"
        ]
      },
      {
        "tag": "span",
        "cls": "",
        "text": "04",
        "color": "rgb(138, 133, 120)",
        "bg": "rgb(246, 245, 241)",
        "y": 1674,
        "hex": "#8a8578",
        "contrast": 3.37,
        "reasons": [
          "low-contrast(3.37)"
        ]
      }
    ]
  },
  {
    "route": "/tjanster/ai-automation",
    "viewport": "desktop",
    "screenshot": ".visual-regression/tjanster_ai-automation.desktop.png",
    "flags": []
  },
  {
    "route": "/ai-karta",
    "viewport": "desktop",
    "screenshot": ".visual-regression/ai-karta.desktop.png",
    "flags": []
  },
  {
    "route": "/arbete",
    "viewport": "desktop",
    "screenshot": ".visual-regression/arbete.desktop.png",
    "flags": []
  },
  {
    "route": "/om",
    "viewport": "desktop",
    "screenshot": ".visual-regression/om.desktop.png",
    "flags": []
  },
  {
    "route": "/kontakt",
    "viewport": "desktop",
    "screenshot": ".visual-regression/kontakt.desktop.png",
    "flags": []
  },
  {
    "route": "/integritetspolicy",
    "viewport": "desktop",
    "screenshot": ".visual-regression/integritetspolicy.desktop.png",
    "flags": []
  },
  {
    "route": "/redaktionell-policy",
    "viewport": "desktop",
    "screenshot": ".visual-regression/redaktionell-policy.desktop.png",
    "flags": []
  }
]